[{"DownloadCount":132,"UnixTimestamp":1663693982},{"DownloadCount":131,"UnixTimestamp":1663577675},{"DownloadCount":130,"UnixTimestamp":1663091292},{"DownloadCount":129,"UnixTimestamp":1662915182},{"DownloadCount":128,"UnixTimestamp":1662794370},{"DownloadCount":127,"UnixTimestamp":1662549891},{"DownloadCount":126,"UnixTimestamp":1662489141},{"DownloadCount":125,"UnixTimestamp":1662420396},{"DownloadCount":124,"UnixTimestamp":1662253764},{"DownloadCount":123,"UnixTimestamp":1661925488},{"DownloadCount":122,"UnixTimestamp":1661502269},{"DownloadCount":121,"UnixTimestamp":1661286437},{"DownloadCount":120,"UnixTimestamp":1661280058},{"DownloadCount":119,"UnixTimestamp":1661211574},{"DownloadCount":118,"UnixTimestamp":1661199640},{"DownloadCount":117,"UnixTimestamp":1661116713},{"DownloadCount":115,"UnixTimestamp":1661103108},{"DownloadCount":114,"UnixTimestamp":1661011523},{"DownloadCount":113,"UnixTimestamp":1660892238},{"DownloadCount":112,"UnixTimestamp":1660887401},{"DownloadCount":111,"UnixTimestamp":1660841959},{"DownloadCount":110,"UnixTimestamp":1660624237},{"DownloadCount":109,"UnixTimestamp":1660525805},{"DownloadCount":108,"UnixTimestamp":1660251016},{"DownloadCount":107,"UnixTimestamp":1659885703},{"DownloadCount":106,"UnixTimestamp":1659768274},{"DownloadCount":105,"UnixTimestamp":1659567331},{"DownloadCount":104,"UnixTimestamp":1659470682},{"DownloadCount":104,"UnixTimestamp":1659470682},{"DownloadCount":104,"UnixTimestamp":1659468070},{"DownloadCount":104,"UnixTimestamp":1659468070},{"DownloadCount":104,"UnixTimestamp":1659437853},{"DownloadCount":103,"UnixTimestamp":1659319962},{"DownloadCount":102,"UnixTimestamp":1658738999},{"DownloadCount":102,"UnixTimestamp":1658738999},{"DownloadCount":102,"UnixTimestamp":1658658874},{"DownloadCount":101,"UnixTimestamp":1658549007},{"DownloadCount":98,"UnixTimestamp":1658344819},{"DownloadCount":97,"UnixTimestamp":1658323757},{"DownloadCount":97,"UnixTimestamp":1658323757},{"DownloadCount":97,"UnixTimestamp":1658280529},{"DownloadCount":96,"UnixTimestamp":1658140618},{"DownloadCount":95,"UnixTimestamp":1658079460},{"DownloadCount":93,"UnixTimestamp":1657425934},{"DownloadCount":92,"UnixTimestamp":1657382064},{"DownloadCount":91,"UnixTimestamp":1657307720},{"DownloadCount":90,"UnixTimestamp":1657257546},{"DownloadCount":90,"UnixTimestamp":1657257546},{"DownloadCount":90,"UnixTimestamp":1656818556},{"DownloadCount":89,"UnixTimestamp":1656760556},{"DownloadCount":88,"UnixTimestamp":1656329479},{"DownloadCount":87,"UnixTimestamp":1656328378},{"DownloadCount":86,"UnixTimestamp":1656327639},{"DownloadCount":85,"UnixTimestamp":1656321849},{"DownloadCount":84,"UnixTimestamp":1656114366},{"DownloadCount":83,"UnixTimestamp":1656093140},{"DownloadCount":82,"UnixTimestamp":1655665688},{"DownloadCount":81,"UnixTimestamp":1655627722},{"DownloadCount":80,"UnixTimestamp":1655622155},{"DownloadCount":78,"UnixTimestamp":1655343645},{"DownloadCount":77,"UnixTimestamp":1655171222},{"DownloadCount":76,"UnixTimestamp":1654829020},{"DownloadCount":75,"UnixTimestamp":1654710272},{"DownloadCount":74,"UnixTimestamp":1654303750},{"DownloadCount":73,"UnixTimestamp":1654171212},{"DownloadCount":72,"UnixTimestamp":1654170384},{"DownloadCount":71,"UnixTimestamp":1653884887},{"DownloadCount":70,"UnixTimestamp":1653817125},{"DownloadCount":69,"UnixTimestamp":1653787976},{"DownloadCount":68,"UnixTimestamp":1653782175},{"DownloadCount":67,"UnixTimestamp":1653781764},{"DownloadCount":66,"UnixTimestamp":1653781016},{"DownloadCount":64,"UnixTimestamp":1653766532},{"DownloadCount":63,"UnixTimestamp":1653763981},{"DownloadCount":62,"UnixTimestamp":1653747857},{"DownloadCount":61,"UnixTimestamp":1653743481},{"DownloadCount":58,"UnixTimestamp":1653737234},{"DownloadCount":57,"UnixTimestamp":1653733340},{"DownloadCount":56,"UnixTimestamp":1653731437},{"DownloadCount":55,"UnixTimestamp":1653663083},{"DownloadCount":54,"UnixTimestamp":1653643574},{"DownloadCount":53,"UnixTimestamp":1653638098},{"DownloadCount":52,"UnixTimestamp":1653635543},{"DownloadCount":16,"UnixTimestamp":1653528231},{"DownloadCount":16,"UnixTimestamp":1653528231}]